.coveragerc
.dockerignore
.gitattributes
.pre-commit-config.yaml
.zenodo.json
CITATION.cff
CODE_OF_CONDUCT.md
CONTRIBUTING.md
ChangeLog
LICENSE
README.md
requirements.sh
requirements.txt
setup.cfg
setup.py
strategy.ini
.github/workflows/publish-pypi.yml
.github/workflows/unit-tests.yml
bin/prefix_commit_jira.sh
docs/.readthedocs.yaml
docs/Makefile
docs/README.md
docs/conf.py
docs/generate_schema_csv.py
docs/index.rst
docs/installation.md
docs/make.bat
docs/requirements.txt
docs/bad_project/index.rst
docs/bad_project/help/contact.md
docs/bad_project/help/glossary.md
docs/bad_project/help/index.rst
docs/bad_project/overview/background.md
docs/bad_project/overview/dashboard_data.md
docs/bad_project/overview/dashboard_sources.csv
docs/bad_project/overview/dashboard_title_sources.csv
docs/bad_project/overview/faq.md
docs/bad_project/overview/how_works.md
docs/bad_project/overview/index.rst
docs/logos/crossref-events.svg
docs/logos/crossref-metadata.svg
docs/logos/doab.png
docs/logos/fulcrum.png
docs/logos/google_analytics.svg
docs/logos/google_books.svg
docs/logos/irus.png
docs/logos/jstor.svg
docs/logos/oapen.png
docs/logos/oapen_irus_uk.png
docs/logos/onix.svg
docs/logos/thoth.png
docs/logos/ucl.svg
docs/oaebu_workflows/index.rst
docs/oaebu_workflows/license.rst
docs/oaebu_workflows/static/onix_workflow_1.png
docs/oaebu_workflows/static/onix_workflow_2.png
docs/oaebu_workflows/static/onix_workflow_3.png
docs/oaebu_workflows/static/onix_workflow_all.png
docs/oaebu_workflows/telescopes/crossref_events.md
docs/oaebu_workflows/telescopes/crossref_metadata.md
docs/oaebu_workflows/telescopes/google_analytics.md
docs/oaebu_workflows/telescopes/google_books.md
docs/oaebu_workflows/telescopes/index.rst
docs/oaebu_workflows/telescopes/irus_fulcrum.md
docs/oaebu_workflows/telescopes/irus_oapen.md
docs/oaebu_workflows/telescopes/jstor.md
docs/oaebu_workflows/telescopes/oapen_metadata.md
docs/oaebu_workflows/telescopes/onix.md
docs/oaebu_workflows/telescopes/thoth.md
oaebu_workflows.egg-info/PKG-INFO
oaebu_workflows.egg-info/SOURCES.txt
oaebu_workflows.egg-info/dependency_links.txt
oaebu_workflows.egg-info/not-zip-safe
oaebu_workflows.egg-info/pbr.json
oaebu_workflows.egg-info/requires.txt
oaebu_workflows.egg-info/top_level.txt
