Metadata-Version: 2.1
Name: oaebu-workflows
Version: 2023.12.0
Summary: Oaebu Workflows provides Apache Airflow Workflows for fetching, processing and analysing data about open access books.
Home-page: https://github.com/The-Academic-Observatory/oaebu-workflows
Author: Curtin University
Author-email: agent@observatory.academy
License: Apache License Version 2.0
Project-URL: Bug Tracker, https://github.com/The-Academic-Observatory/oaebu-workflows/issues
Project-URL: Documentation, https://oaebu-workflows.readthedocs.io/en/latest/
Project-URL: Source Code, https://github.com/The-Academic-Observatory/oaebu-workflows
Keywords: science,data,workflows,academic institutes,oaebu-workflows
Classifier: Development Status :: 2 - Pre-Alpha
Classifier: Environment :: Console
Classifier: Environment :: Web Environment
Classifier: Intended Audience :: Developers
Classifier: Intended Audience :: Science/Research
Classifier: License :: OSI Approved :: Apache Software License
Classifier: Operating System :: OS Independent
Classifier: Programming Language :: Python :: 3 :: Only
Classifier: Programming Language :: Python :: 3
Classifier: Programming Language :: Python :: 3.10
Classifier: Topic :: Scientific/Engineering
Classifier: Topic :: Software Development :: Libraries
Classifier: Topic :: Software Development :: Libraries :: Python Modules
Classifier: Topic :: Utilities
Requires-Python: >=3.10
Provides-Extra: tests
License-File: LICENSE
